pandas_dq.py
pandas_dq-1.29.dist-info/LICENSE
pandas_dq-1.29.dist-info/METADATA
pandas_dq-1.29.dist-info/WHEEL
pandas_dq-1.29.dist-info/top_level.txt
pandas_dq-1.29.dist-info/RECORD
