Metadata-Version: 2.1
Name: pandas-dq
Version: 1.29
Summary: Clean your data using a scikit-learn transformer in a single line of code
Home-page: https://github.com/AutoViML/pandas_dq
Author: Ram Seshadri
License: Apache License 2.0
Platform: UNKNOWN
Classifier: Programming Language :: Python :: 3
Classifier: Operating System :: OS Independent
Requires-Dist: numpy (>=1.21.5)
Requires-Dist: pandas (>=1.3.5)
Requires-Dist: scikit-learn (>=0.24.2)
